{
	"backtraceGraph" : 
	{
		"commands" : 
		[
			"install"
		],
		"files" : 
		[
			"src/external_libs/grpc/third_party/re2/CMakeLists.txt"
		],
		"nodes" : 
		[
			{
				"file" : 0
			},
			{
				"command" : 0,
				"file" : 0,
				"line" : 155,
				"parent" : 0
			},
			{
				"command" : 0,
				"file" : 0,
				"line" : 157,
				"parent" : 0
			},
			{
				"command" : 0,
				"file" : 0,
				"line" : 162,
				"parent" : 0
			}
		]
	},
	"installers" : 
	[
		{
			"backtrace" : 1,
			"component" : "Unspecified",
			"destination" : "include/re2",
			"paths" : 
			[
				"src/external_libs/grpc/third_party/re2/re2/filtered_re2.h",
				"src/external_libs/grpc/third_party/re2/re2/re2.h",
				"src/external_libs/grpc/third_party/re2/re2/set.h",
				"src/external_libs/grpc/third_party/re2/re2/stringpiece.h"
			],
			"type" : "file"
		},
		{
			"backtrace" : 2,
			"component" : "Unspecified",
			"destination" : "lib",
			"paths" : 
			[
				"src/external_libs/grpc/third_party/re2/libre2.a"
			],
			"targetId" : "re2::@61adf3e496987ba96a4a",
			"targetIndex" : 142,
			"type" : "target"
		},
		{
			"backtrace" : 3,
			"component" : "Unspecified",
			"destination" : "lib/cmake/re2",
			"exportName" : "re2Config",
			"exportTargets" : 
			[
				{
					"id" : "re2::@61adf3e496987ba96a4a",
					"index" : 142
				}
			],
			"paths" : 
			[
				"src/external_libs/grpc/third_party/re2/CMakeFiles/Export/2163157bb4e691faa63e00f4fb3aeb7d/re2Config.cmake"
			],
			"type" : "export"
		}
	],
	"paths" : 
	{
		"build" : "src/external_libs/grpc/third_party/re2",
		"source" : "src/external_libs/grpc/third_party/re2"
	}
}
